LICENSE
README.md
setup.cfg
setup.py
PragyanX/__init__.py
PragyanX/developers.py
PragyanX/version.py
PragyanX/data/__init__.py
PragyanX/data/spamx.py
PragyanX/data/tags.py
PragyanX/data/usage_data.py
PragyanX/data/vars.py
PragyanX/docs/__init__.py
PragyanX/functions/__init__.py
PragyanX/functions/admins.py
PragyanX/functions/broadcast.py
PragyanX/functions/custom_filters.py
PragyanX/functions/get_info.py
PragyanX/functions/get_time.py
PragyanX/functions/get_user.py
PragyanX/functions/list.py
PragyanX/functions/purges.py
PragyanX/functions/scraper.py
PragyanX/functions/spamx.py
PragyanX/functions/voicechat.py
PragyanX/functions/watchers.py
PragyanX/functions/welcome_message.py
pyPragyanX.egg-info/PKG-INFO
pyPragyanX.egg-info/SOURCES.txt
pyPragyanX.egg-info/dependency_links.txt
pyPragyanX.egg-info/requires.txt
pyPragyanX.egg-info/top_level.txt
twatcher/__init__.py