Metadata-Version: 2.1
Name: pyPragyanX
Version: 1.1.4
Summary: A Pyrogram based functional module.
Home-page: https://github.com/PragyanIITIAN/pyPragyanX
Author: Pragyan IITIAN
Author-email: pragyaniitian@gmail.com
License: GNU General Public License v3.0
Keywords: telegram,pyPragyanX,PragyanX,pyrogram,functions,py-PragyanX
Classifier: Framework :: AsyncIO
Classifier: Development Status :: 3 - Alpha
Classifier: Intended Audience :: Developers
Classifier: License :: OSI Approved :: GNU General Public License v2 or later (GPLv2+)
Classifier: Natural Language :: English
Classifier: Operating System :: OS Independent
Classifier: Programming Language :: Python :: 3.7
Classifier: Programming Language :: Python :: 3.8
Classifier: Programming Language :: Python :: 3.9
Classifier: Programming Language :: Python :: 3.10
Classifier: Topic :: Internet :: WWW/HTTP
Classifier: Topic :: Software Development :: Libraries
Classifier: Topic :: Software Development :: Build Tools
License-File: LICENSE
